LICENSE.txt
MANIFEST.in
README.md
setup.cfg
setup.py
govtrack/__init__.py
govtrack/__init__.pyc
govtrack/api.py
govtrack/api.pyc
govtrack/run_tests.py
govtrack/tests.py
govtrack/tests.pyc
govtrack.egg-info/PKG-INFO
govtrack.egg-info/SOURCES.txt
govtrack.egg-info/dependency_links.txt
govtrack.egg-info/requires.txt
govtrack.egg-info/top_level.txt