Metadata-Version: 1.1
Name: govtrack
Version: 0.1
Summary: A Python library for the GovTrack.us API v2.
Home-page: https://github.com/cdelguercio/govtrack-python
Author: Chris Del Guercio
Author-email: cdelguercio@gmail.com
License: UNKNOWN
Download-URL: https://github.com/cdelguercio/govtrack-python/tarball/0.1
Keywords: govtrack,api,python
Platform: UNKNOWN
